<?xml version="1.0" encoding="utf-8" ?>
<dwsync>
<file name="CHANGELOG.txt" server="utopicus.teachnova.net/2011_09_18-openatrium-comunidad-1.0/" local="129659446780000000" remote="129811429200000000" />
<file name="LICENSE.txt" server="utopicus.teachnova.net/2011_09_18-openatrium-comunidad-1.0/" local="129607626200000000" remote="129811429200000000" />
<file name="README.txt" server="utopicus.teachnova.net/2011_09_18-openatrium-comunidad-1.0/" local="129659446780000000" remote="129811429200000000" />
<file name="services.admin.inc" server="utopicus.teachnova.net/2011_09_18-openatrium-comunidad-1.0/" local="129659446780000000" remote="129811429200000000" />
<file name="services.authentication.api.php" server="utopicus.teachnova.net/2011_09_18-openatrium-comunidad-1.0/" local="129659446780000000" remote="129811429200000000" />
<file name="services.css" server="utopicus.teachnova.net/2011_09_18-openatrium-comunidad-1.0/" local="129659446780000000" remote="129811429200000000" />
<file name="services.info" server="utopicus.teachnova.net/2011_09_18-openatrium-comunidad-1.0/" local="129659490440000000" remote="129811429200000000" />
<file name="services.install" server="utopicus.teachnova.net/2011_09_18-openatrium-comunidad-1.0/" local="129659446780000000" remote="129811429200000000" />
<file name="services.module" server="utopicus.teachnova.net/2011_09_18-openatrium-comunidad-1.0/" local="129659446780000000" remote="129811429200000000" />
<file name="services.resource_build.inc" server="utopicus.teachnova.net/2011_09_18-openatrium-comunidad-1.0/" local="129659446780000000" remote="129811429200000000" />
<file name="services.runtime.inc" server="utopicus.teachnova.net/2011_09_18-openatrium-comunidad-1.0/" local="129659446780000000" remote="129811429200000000" />
<file name="services.servers.api.php" server="utopicus.teachnova.net/2011_09_18-openatrium-comunidad-1.0/" local="129659446780000000" remote="129811429200000000" />
<file name="services.services.api.php" server="utopicus.teachnova.net/2011_09_18-openatrium-comunidad-1.0/" local="129659446780000000" remote="129811429200000000" />
</dwsync>