<?xml version="1.0" encoding="utf-8" ?>
<dwsync>
<file name="logintoboggan_rules.info" server="ftp.tahiche.es//public/nuevarevista/" local="129465610160000000" remote="129620361600000000" />
<file name="logintoboggan_rules.module" server="ftp.tahiche.es//public/nuevarevista/" local="129434747320000000" remote="129620361600000000" />
<file name="logintoboggan_rules.rules.inc" server="ftp.tahiche.es//public/nuevarevista/" local="129434747320000000" remote="129620361600000000" />
<file name="README.txt" server="ftp.tahiche.es//public/nuevarevista/" local="129434747320000000" remote="129620361600000000" />
<file name="logintoboggan_rules.info" server="utopicus.teachnova.net/2011_09_18-openatrium-comunidad-1.0/" local="129465610160000000" remote="129805393200000000" />
<file name="logintoboggan_rules.module" server="utopicus.teachnova.net/2011_09_18-openatrium-comunidad-1.0/" local="129434747320000000" remote="129805393200000000" />
<file name="logintoboggan_rules.rules.inc" server="utopicus.teachnova.net/2011_09_18-openatrium-comunidad-1.0/" local="129434747320000000" remote="129805393200000000" />
<file name="README.txt" server="utopicus.teachnova.net/2011_09_18-openatrium-comunidad-1.0/" local="129434747320000000" remote="129805393200000000" />
</dwsync>